static_di/__init__.py
static_di/class_dependency.py
static_di/default_config.py
static_di/dependency_injector.py
static_di/fetch_dependency.py
static_di/get_signature_without_self.py
static_di/resolve_arguments.py
static_di/scope.py
static_di/value_dependency.py
static_di/interfaces/__init__.py
static_di/interfaces/i_config.py
static_di/interfaces/i_dependency.py
static_di/interfaces/i_dependency_injector.py
static_di/interfaces/i_fetch_dependency.py
static_di/interfaces/i_resolve_arguments.py
static_di/interfaces/i_scope.py
static_di-0.1.0.dist-info/METADATA
static_di-0.1.0.dist-info/WHEEL
static_di-0.1.0.dist-info/top_level.txt
static_di-0.1.0.dist-info/RECORD
