Metadata-Version: 2.4
Name: static-di
Version: 0.1.0
Summary: A type-based dependency injection library with scoping capabilities.
Author: Filip Dudziński
License-Expression: MIT
Project-URL: GitHub, https://github.com/FIIFE/Static-DI
Keywords: dependency injection,type based,scoped,inversion of control,ioc,di,typed,injection,annotation based
Classifier: Development Status :: 4 - Beta
Requires-Python: >=3.11
Requires-Dist: typeguard>=4.4.2
